README.rst
setup.py
django_smtp_alternative/__init__.py
django_smtp_alternative.egg-info/PKG-INFO
django_smtp_alternative.egg-info/SOURCES.txt
django_smtp_alternative.egg-info/dependency_links.txt
django_smtp_alternative.egg-info/requires.txt
django_smtp_alternative.egg-info/top_level.txt