Metadata-Version: 1.1
Name: django-smtp-alternative
Version: 0.0.1a
Summary: Django email backend providing sending with alternative SMTP server if primary server fails
Home-page: https://github.com/COEXCZ/django_smtp_alternative
Author: Jan Češpivo, COEX CZ s.r.o (http://www.coex.cz)
Author-email: jan.cespivo@gmail.com
License: LGPLv3
Platform: UNKNOWN
Classifier: Development Status :: 5 - Production/Stable
Classifier: Environment :: Web Environment
Classifier: Intended Audience :: Developers
Classifier: License :: OSI Approved :: GNU Lesser General Public License v3 (LGPLv3)
Classifier: Operating System :: OS Independent
Classifier: Programming Language :: Python
